.coveragerc
.gitignore
.travis.yml
LICENSE
MANIFEST.in
Makefile
README.rst
THANKS.rst
setup.cfg
setup.py
sitecustomize.py
tox.ini
chaussette/__init__.py
chaussette/_paste.py
chaussette/server.py
chaussette/util.py
chaussette.egg-info/PKG-INFO
chaussette.egg-info/SOURCES.txt
chaussette.egg-info/dependency_links.txt
chaussette.egg-info/entry_points.txt
chaussette.egg-info/not-zip-safe
chaussette.egg-info/requires.txt
chaussette.egg-info/top_level.txt
chaussette/backend/__init__.py
chaussette/backend/_bjoern.py
chaussette/backend/_eventlet.py
chaussette/backend/_fastgevent.py
chaussette/backend/_gevent.py
chaussette/backend/_geventwebsocket.py
chaussette/backend/_geventws4py.py
chaussette/backend/_meinheld.py
chaussette/backend/_socketio.py
chaussette/backend/_tornado.py
chaussette/backend/_waitress.py
chaussette/backend/_wsgiref.py
chaussette/tests/__init__.py
chaussette/tests/support.py
chaussette/tests/test_backend.py
chaussette/tests/test_paste.py
chaussette/tests/test_server.py
chaussette/tests/test_util.py
docs/Makefile
docs/make.bat
docs/source/conf.py
docs/source/index.rst
docs/source/images/chaussette.png
examples/__init__.py
examples/flaskapp.py
examples/tornadoapp.py
examples/simple_chat/README.txt
examples/simple_chat/__init__.py
examples/simple_chat/chat.html
examples/simple_chat/chat.py
examples/simple_chat/static/WebSocketMain.swf
examples/simple_chat/static/jquery-1.6.1.min.js
examples/simple_chat/static/socket.io.js
examples/simple_chat/static/css/style.css