Metadata-Version: 1.1
Name: chaussette
Version: 1.3.0
Summary: A WSGI Server for Circus
Home-page: http://chaussette.readthedocs.org
Author: Mozilla Foundation & Contributors
Author-email: services-dev@lists.mozila.org
License: UNKNOWN
Platform: UNKNOWN
Classifier: Programming Language :: Python
Classifier: Programming Language :: Python :: 2
Classifier: Programming Language :: Python :: 2.6
Classifier: Programming Language :: Python :: 2.7
Classifier: Programming Language :: Python :: 3
Classifier: Programming Language :: Python :: 3.3
Classifier: Programming Language :: Python :: 3.4
Classifier: License :: OSI Approved :: Apache Software License
Classifier: Development Status :: 3 - Alpha
